[
    {
        "title": "Portuguese Level II",
        "subjectCode": "PTGS",
        "courseCode": "10200",
        "instructor": [
            "Carolina Alvim Ferreira"
        ],
        "description": "Continuation of PTGS 10100.",
        "capacity": 0,
        "credits": [
            3,
            3
        ],
        "term": "Spring 2023"
    },
    {
        "title": "Portuguese Level IV",
        "subjectCode": "PTGS",
        "courseCode": "20200",
        "instructor": [
            "Thiago Brito Santos"
        ],
        "description": "Continuation of PTGS 20100.",
        "capacity": 0,
        "credits": [
            3,
            3
        ],
        "term": "Spring 2023"
    }
]